{
    "ch": [
        "ùa",
        "ùa",
        "ùa",
        "ùa",
        "ốn",
        "ùa",
        "ùa",
        "ùa",
        "ùa",
        "ính",
        "ùa",
        "ùa",
        "uông,",
        "ùa,",
        "ùa,",
        "o",
        "ùa",
        "ùa",
        "o",
        "ùa",
        "ùa,",
        "ùa",
        "ữ",
        "ữ",
        "ùa",
        "ùa",
        "ính",
        "ữ",
        "uông.",
        "uông",
        "ùa",
        "ồng",
        "ính.",
        "ùa",
        "ùa",
        "ùa",
        "ùa",
        "ín",
        "ùa",
        "o",
        "ân,",
        "ùa",
        "ữa",
        "ùa",
        "úa",
        "ùa",
        "ấp",
        "ùa",
        "ùa.",
        "ào",
        "ức",
        "ùa,",
        "uông",
        "ùa",
        "ùa",
        "úa",
        "o",
        "ùa,",
        "úa.",
        "ùa.",
        "ùa,",
        "ùa.",
        "ùa",
        "uyến",
        "ùa",
        "ùa",
        "ú"
    ],
    "tr": [
        "ấn",
        "ên",
        "úc",
        "ung",
        "ần.",
        "ị",
        "úc,",
        "ấn",
        "ong",
        "ấn",
        "ung",
        "ong",
        "ên",
        "ần).",
        "ong",
        "ùng",
        "ạng",
        "ùng",
        "ị",
        "ấn",
        "ấn",
        "úc",
        "ấn",
        "ên",
        "ưng",
        "ong",
        "ải",
        "ình",
        "úc",
        "ong",
        "ên",
        "ấn",
        "ình",
        "ên",
        "ục",
        "ái",
        "ong",
        "ên",
        "ong",
        "ị",
        "ụ",
        "ì",
        "ấn",
        "ưng",
        "í",
        "í",
        "ùng",
        "úc",
        "úc",
        "ong",
        "ịnh),",
        "ùng",
        "ải",
        "ong",
        "anh",
        "ong",
        "ùng",
        "ấn",
        "ai",
        "ong",
        "ấn",
        "ên",
        "ần",
        "ụ",
        "ì",
        "í",
        "iều",
        "ịnh",
        "ồng",
        "ị",
        "ồng",
        "ước",
        "ong",
        "ong",
        "ấn"
    ],
    "qu": [
        "ốc",
        "an",
        "ốc",
        "an,",
        "ốc",
        "ốc,",
        "an",
        "ốc",
        "en",
        "an",
        "ốc",
        "anh",
        "ý",
        "a",
        "an",
        "anh,",
        "an",
        "an",
        "a",
        "ốc",
        "ý",
        "ý.",
        "ý.",
        "ốc,",
        "ốc",
        "a",
        "yền",
        "ốc",
        "ốc",
        "ốc",
        "anh",
        "an",
        "an",
        "an",
        "ốc"
    ],
    "(": [
        "鎭國寺)",
        "quận",
        "hà",
        "lý",
        "1615),",
        "thời",
        "thời",
        "40",
        "工).",
        "thế",
        "được",
        "thời",
        "trên",
        "dòng",
        "1639)"
    ],
    "n": [
        "ằm",
        "ăm,",
        "hất",
        "ội.",
        "ghiêm,",
        "hã",
        "ền",
        "ước",
        "hững",
        "ổi",
        "hiều",
        "goài",
        "am.",
        "am",
        "ội,",
        "guyên",
        "am",
        "ền",
        "hà",
        "guyên",
        "hà",
        "ăm",
        "guyên",
        "guyễn",
        "ăm",
        "ày.",
        "hà",
        "guyễn,",
        "ăm",
        "ăm",
        "hưng",
        "hân",
        "gày",
        "ay.",
        "hất",
        "ước",
        "gọt",
        "hất",
        "ội.",
        "hỏ",
        "ghìn",
        "ăm",
        "gôi",
        "ơi",
        "hững",
        "gôi",
        "hà",
        "hưng",
        "iệm",
        "ôm:",
        "gựa",
        "on",
        "hững",
        "gôi",
        "am,",
        "ội",
        "guyên",
        "hiều",
        "hà",
        "gôi",
        "hà",
        "ối",
        "hà",
        "gôi",
        "ằm",
        "hà",
        "hà",
        "ay",
        "ăm",
        "át.",
        "ày",
        "ăm",
        "ăm",
        "ăm",
        "ày",
        "ội",
        "ăm",
        "hã,",
        "am,",
        "hư",
        "ghĩa",
        "hận",
        "ăm",
        "hiên,",
        "hiều",
        "ên",
        "ăm",
        "am",
        "gôi",
        "hất",
        "ăm",
        "iên",
        "ăm",
        "ăm",
        "ội",
        "ghị",
        "am",
        "ày",
        "ăm",
        "gợi:",
        "gắm",
        "ước,",
        "hã",
        "hân",
        "hiều",
        "ăm",
        "ơi",
        "hà",
        "ăm",
        "ăm",
        "gày",
        "ăm",
        "gày",
        "ăm",
        "hân",
        "am",
        "gày",
        "ăm",
        "ga",
        "ội",
        "ghị",
        "iên",
        "ga",
        "ội",
        "am",
        "goài"
    ],
    "m": [
        "ột",
        "ột",
        "ênh",
        "ang.",
        "ở",
        "inh",
        "ạng",
        "ột",
        "ột",
        "ột",
        "ột",
        "ặt",
        "ặt",
        "ôn",
        "ở",
        "ặt",
        "ột",
        "ái",
        "ột",
        "ột",
        "ộ",
        "ỗi",
        "ỗi",
        "ột",
        "à",
        "ở",
        "ừng",
        "ây",
        "ặt",
        "ộng",
        "ão",
        "inh",
        "ạng",
        "edvedev"
    ],
    "h": [
        "òn",
        "ồ",
        "ồ),",
        "à",
        "ợp",
        "ài",
        "oà",
        "ồ",
        "út",
        "óa",
        "oa,",
        "ồng.",
        "ưng",
        "oa",
        "àn",
        "y",
        "òn",
        "ồ",
        "à",
        "ai",
        "ồ",
        "ang",
        "iếm",
        "àng",
        "oàn",
        "ồ",
        "iện",
        "ình",
        "iện",
        "oàn",
        "ai",
        "ầu",
        "ết",
        "ương",
        "ình",
        "ướng",
        "ai",
        "ương",
        "ai",
        "ành",
        "iện",
        "ựu",
        "ưng",
        "ình",
        "oa)",
        "à",
        "ội",
        "ội",
        "àm",
        "iện",
        "oá",
        "ậu",
        "oang",
        "ợi,",
        "iệu",
        "à",
        "ội",
        "ợi",
        "ưng",
        "ồ",
        "ọc",
        "oà",
        "oà",
        "ậu",
        "ành",
        "ương",
        "à",
        "ội",
        "ai",
        "ình",
        "à"
    ],
    "đ": [
        "ảo",
        "ông",
        "ược",
        "ời",
        "iểm",
        "ồ",
        "iển",
        "ế,",
        "ến",
        "ời",
        "ược",
        "ê",
        "iện",
        "ược",
        "ã",
        "ầu",
        "ời",
        "ược",
        "úc",
        "ắp",
        "ến",
        "ể",
        "ến",
        "ồng",
        "ổi",
        "ời",
        "ã",
        "ược",
        "ến",
        "ảo",
        "ộng",
        "ây",
        "ược",
        "ổi",
        "ường",
        "ại",
        "ịa.",
        "ối",
        "ường",
        "ứng",
        "ường,",
        "iện",
        "ường",
        "iện",
        "iện",
        "ường",
        "ang",
        "ổ",
        "ầu",
        "ời",
        "ộ",
        "ài",
        "ược",
        "ặt",
        "à",
        "á",
        "ỉnh",
        "ài",
        "á",
        "ược",
        "ối",
        "ề",
        "ộ",
        "ến",
        "ồng",
        "ã",
        "ối",
        "ó",
        "ề",
        "ều",
        "ược",
        "ã",
        "ược",
        "ó",
        "ịa",
        "ã",
        "ược",
        "ể",
        "ại",
        "ỉnh",
        "ợt",
        "ồng",
        "ã",
        "áy",
        "ời",
        "ường",
        "ộng)",
        "ặc",
        "ã",
        "ến",
        "ể",
        "àm",
        "ạo.",
        "ến",
        "ể",
        "ến",
        "ồng",
        "ể",
        "ộ",
        "ờ",
        "ến",
        "ề",
        "ộ",
        "ến",
        "ến",
        "ến",
        "ại"
    ],
    "ph": [
        "ía",
        "ật",
        "ật",
        "ật",
        "ụ,",
        "ủ,",
        "ố,",
        "á",
        "ía",
        "ương",
        "ật",
        "ía",
        "ải",
        "ạm",
        "ía",
        "o",
        "ật",
        "ẩm",
        "ật",
        "ật",
        "áp\".",
        "a",
        "ong",
        "ế,",
        "ương",
        "ạm",
        "ật",
        "í",
        "ong",
        "ật",
        "ật",
        "ật"
    ],
    "t": [
        "ây",
        "ây",
        "hăng",
        "ính",
        "hanh",
        "ĩnh",
        "âm",
        "hành",
        "hăng",
        "hời",
        "hời",
        "iếng",
        "hiêng,",
        "hu",
        "ín",
        "ử",
        "ham",
        "heo",
        "ừ",
        "ích",
        "hì",
        "ừ",
        "hời",
        "iền",
        "ại",
        "hôn",
        "húy",
        "iếp",
        "ục",
        "u,",
        "ôn",
        "ạo",
        "u,",
        "ượng.",
        "hăm",
        "u",
        "hiệu",
        "hăm",
        "iền",
        "iền,",
        "ên",
        "ên",
        "ừ",
        "ông",
        "oạ",
        "hời",
        "ây",
        "hưa",
        "hớt,",
        "hú",
        "ồn.",
        "hời",
        "ồn",
        "ại",
        "oàn.",
        "hự",
        "hành...",
        "hể",
        "hiện",
        "ổng",
        "hể",
        "hành",
        "ình",
        "âm",
        "iện",
        "ai",
        "ục/",
        "hiền",
        "hất",
        "ự",
        "heo",
        "ắc",
        "iền",
        "hiêu",
        "hượng",
        "hành",
        "iền",
        "ây.",
        "hiêu",
        "hượng",
        "hượng",
        "ổ",
        "ấm",
        "iến",
        "hích",
        "u",
        "hời",
        "húc",
        "háp",
        "ừ",
        "háp",
        "háp",
        "ầng,",
        "ầng",
        "háp",
        "ượng",
        "háp",
        "ầng",
        "háp",
        "ổng",
        "hống",
        "ặng",
        "hăm",
        "hượng",
        "oạ",
        "hích",
        "hanh",
        "hích",
        "ượng",
        "ính",
        "ính",
        "uệ",
        "hượng.",
        "ất",
        "hể",
        "ượng",
        "ích",
        "uy",
        "u,",
        "ạp",
        "hời",
        "u,",
        "hời",
        "ây",
        "hời",
        "u",
        "u",
        "ái",
        "ạo",
        "ự",
        "iến",
        "u",
        "hăng",
        "hượng",
        "hế",
        "hứ",
        "ổ",
        "ại",
        "háng",
        "oán",
        "u",
        "ỷ",
        "ạo",
        "ự",
        "iến",
        "hứ",
        "iếng",
        "ỉnh",
        "ục...\"",
        "hiền",
        "ăng",
        "hống",
        "hảo",
        "hiền",
        "hông",
        "hiền",
        "hiền",
        "ịnh",
        "hiền",
        "hiền",
        "ế",
        "hiền",
        "ịnh",
        "ào",
        "hượngkim",
        "ử",
        "hượng",
        "hích",
        "hanh",
        "hăm",
        "ông,",
        "hái",
        "ăng",
        "hờ",
        "hành",
        "hăm,",
        "u",
        "hiệu",
        "hăm",
        "iền",
        "iền",
        "u",
        "háng",
        "ổng",
        "hống",
        "hăm",
        "ặng",
        "òa",
        "am",
        "háng",
        "ổng",
        "hống",
        "hắp",
        "ham",
        "háng",
        "ổng",
        "hống",
        "ham",
        "hường",
        "hứ",
        "hêm",
        "iểu",
        "hừa",
        "hừa",
        "hích"
    ],
    "c": [
        "ó",
        "oi",
        "ó",
        "ổ",
        "ảnh",
        "ủa",
        "ủa",
        "ửa",
        "ũ",
        "ung",
        "ác",
        "ông",
        "ó",
        "ảnh",
        "ủa",
        "ư",
        "ó",
        "ác",
        "ây",
        "òn",
        "ó",
        "ả",
        "ùng",
        "ủa",
        "ảnh",
        "ó",
        "ông",
        "ủa",
        "ảnh",
        "ủa",
        "ư",
        "ửa",
        "ó",
        "âu",
        "ửa",
        "ấu",
        "ó",
        "ủa",
        "ông",
        "ó",
        "ủa",
        "ông",
        "ó",
        "ổ",
        "ảnh",
        "ó",
        "ao",
        "ó",
        "ửa",
        "ó",
        "ửu",
        "ũng",
        "ây",
        "ả",
        "ủa",
        "ác",
        "ông",
        "ấp",
        "ách",
        "ủa",
        "ác",
        "ác",
        "ảnh",
        "uối",
        "ảnh",
        "ư",
        "ủa",
        "ảnh",
        "a",
        "ao",
        "ảnh",
        "ác",
        "ương",
        "ác",
        "ùng",
        "ác",
        "ao",
        "úng",
        "ung",
        "ủa",
        "ây",
        "ửa",
        "ông",
        "ấp",
        "ao"
    ],
    "l": [
        "ịch",
        "à",
        "âu",
        "ong",
        "ặng",
        "à",
        "ong",
        "ý",
        "ịch",
        "à",
        "inh",
        "à",
        "ịch",
        "ịch",
        "à",
        "ý",
        "ê",
        "ý)",
        "ại",
        "ạng",
        "ớn",
        "à",
        "ê",
        "ạc",
        "ớn",
        "oài",
        "ớn",
        "ịch",
        "inh",
        "ớp",
        "à",
        "à",
        "ang.",
        "à",
        "à",
        "à",
        "à",
        "ưu",
        "ại",
        "ại",
        "ục",
        "ớn",
        "à",
        "iên",
        "ớn",
        "à:",
        "à",
        "à",
        "ịch",
        "ần",
        "ực",
        "ê",
        "ịch",
        "ại",
        "ần",
        "ớn",
        "à",
        "ong",
        "ập",
        "ễ",
        "ong",
        "ần",
        "à",
        "ồng",
        "âng",
        "âng.",
        "ý",
        "an",
        "ần",
        "ạng",
        "ớn",
        "b",
        "b",
        "ần",
        "iên"
    ],
    "s": [
        "ử",
        "ự",
        "ử",
        "ử",
        "ông",
        "oạn",
        "ửa.",
        "ố",
        "inh",
        "ự",
        "ử",
        "ống",
        "ố",
        "ông",
        "ự",
        "ắp",
        "au",
        "ảnh",
        "ĩ",
        "ửa",
        "au",
        "au",
        "ố",
        "en",
        "en",
        "ự",
        "ự",
        "en",
        "inh",
        "ử",
        "ửa",
        "ơn,",
        "ử",
        "ửa",
        "ĩ",
        "oạn",
        "ĩ",
        "oạn,",
        "ư",
        "ư",
        "ư",
        "ư",
        "ư",
        "ư",
        "ư",
        "ư",
        "ửa",
        "en",
        "ửa",
        "ửa",
        "ách"
    ],
    "ở": [
        "",
        "",
        "",
        "",
        ""
    ],
    "-": [
        "",
        "",
        ""
    ],
    "k": [
        "iến",
        "ết",
        "ính",
        "inh",
        "iến",
        "iến",
        "iến",
        "ết",
        "ết",
        "ỉ",
        "iến",
        "iến",
        "ỳ:",
        "inh",
        "ỷ",
        "ỷ",
        "ết"
    ],
    "g": [
        "iữa",
        "iữa",
        "iáo",
        "iá",
        "ần",
        "ọi",
        "ian",
        "iờ",
        "iống",
        "iáo.",
        "ồm",
        "ác",
        "ác",
        "ian,",
        "iữ",
        "ian",
        "ồm",
        "ọi",
        "iáo",
        "iáo",
        "iải",
        "iác,",
        "ia",
        "ia",
        "iáo",
        "iới",
        "ọi",
        "iác",
        "iác",
        "iáo",
        "iáo",
        "iáo"
    ],
    "u": [
        "y",
        "ỷ",
        "ế."
    ],
    "v": [
        "ới",
        "ào",
        "à",
        "ới",
        "ề",
        "à",
        "à",
        "iệt",
        "ăn",
        "iệt",
        "ào",
        "à",
        "à",
        "ăn",
        "ào",
        "ề",
        "iệc",
        "ua",
        "ua",
        "àng",
        "à",
        "ua",
        "à",
        "ào",
        "ực",
        "ừa",
        "à",
        "à",
        "à",
        "ô",
        "ỡ",
        "à",
        "à",
        "iết",
        "ang",
        "iệt",
        "à",
        "à",
        "ới",
        "à",
        "ề",
        "à",
        "à",
        "ăn",
        "iệc",
        "iệc",
        "ào",
        "à",
        "ào",
        "ĩnh",
        "à",
        "iên",
        "òm,",
        "ới",
        "iên",
        "iệt",
        "ô",
        "à",
        "ăn",
        "ào",
        "à",
        "iệt",
        "ào",
        "ào",
        "ăn",
        "ăn)",
        "à",
        "iệt",
        "ào",
        "ăn",
        "ân",
        "iệt",
        "iên",
        "ua",
        "ị",
        "à",
        "ua",
        "ua",
        "àng",
        "à",
        "à",
        "à",
        "iệt",
        "iệt"
    ],
    "r": [
        "ất",
        "ộng.",
        "ất",
        "ừng",
        "ừng",
        "ộng.",
        "ơi",
        "iêng",
        "agiăng",
        "a"
    ],
    "kh": [
        "ách",
        "ai",
        "u",
        "ác",
        "ác",
        "ác",
        "ắt",
        "e",
        "ắc",
        "uôn",
        "i",
        "ông",
        "ông",
        "ỏi",
        "i",
        "oa",
        "oa",
        "iến",
        "ách",
        "uông",
        "ông",
        "oan",
        "ách",
        "ông"
    ],
    "d": [
        "u",
        "i",
        "ựng",
        "ời",
        "ựng",
        "ựng",
        "ân",
        "uy",
        "ân",
        "ân",
        "ãy",
        "iêm,",
        "ài",
        "ựng",
        "i",
        "ựng",
        "o",
        "ưới",
        "i",
        "o",
        "ân",
        "o",
        "ự",
        "o",
        "u",
        "ưới",
        "ịp",
        "u",
        "mitry",
        "ịp",
        "ự",
        "anh"
    ],
    "=": [
        "=",
        "=",
        "=",
        "=",
        "=",
        "=",
        "=",
        "=",
        "=",
        "=",
        "=",
        "=",
        "=",
        "=",
        "=",
        "="
    ],
    "1": [
        "993),",
        "624,",
        "639,",
        "821,",
        "842,",
        "815.",
        "8).",
        "998.",
        "5m.",
        "959.",
        "989.",
        "624,",
        "1/2010.",
        "821,",
        "842,",
        "959,"
    ],
    "5": [
        "41-547),"
    ],
    "y": [
        "",
        "ên"
    ],
    "b": [
        "ờ",
        "ài",
        "ia",
        "an",
        "ạc",
        "an",
        "ắc.",
        "à",
        "ao",
        "ây",
        "ờ",
        "ao",
        "iệt",
        "ản",
        "a",
        "ên",
        "ằng",
        "a",
        "ên",
        "a",
        "ên",
        "ên",
        "ia.",
        "ia.",
        "ia",
        "ài",
        "ắt",
        "ảo",
        "ảo",
        "ằng",
        "ằng",
        "ảo",
        "ồ",
        "ùn",
        "ị",
        "ồ",
        "ản",
        "ị",
        "ối",
        "ị",
        "ia",
        "i",
        "ổ",
        "ổ",
        "ia",
        "i\"",
        "iện",
        "iệt",
        "iến",
        "an",
        "ạc",
        "an",
        "rusat",
        "ồ",
        "ảo"
    ],
    "x": [
        "uân",
        "ung",
        "e",
        "ếp",
        "ây",
        "ứng",
        "ứng",
        "in",
        "anh",
        "anh",
        "em"
    ],
    "4": [
        "3),"
    ],
    "gh": [
        "i",
        "i"
    ],
    "ô": [
        "",
        "",
        "ng",
        ""
    ],
    "a": [
        "",
        "i",
        "sean"
    ],
    "ấ": [
        "n",
        "t",
        "n",
        "n"
    ],
    "\"": [
        "hoa",
        "tái",
        "đứng"
    ],
    "ý": [
        ""
    ],
    ".": [
        "",
        "",
        "",
        "",
        ""
    ],
    "2": [
        "010,",
        "008,",
        "010,"
    ],
    "–": [
        ""
    ],
    "á": [
        "nh"
    ],
    "q": [
        "úan",
        "ủang"
    ],
    "ỷ": [
        ""
    ],
    "p": [
        "ratibha",
        "atil"
    ],
    "ả": [
        "nh"
    ]
}