{
    "n": [
        "hóm",
        "hóm",
        "hóm",
        "hững",
        "gười",
        "ào",
        "hóm",
        "gười",
        "gười",
        "gười",
        "hau",
        "hóm.",
        "ghiên",
        "gười",
        "ghèo",
        "am",
        "ghĩa",
        "hững",
        "gười",
        "iềm",
        "hóm",
        "gười",
        "hóm",
        "ghiên",
        "gười",
        "ghèo",
        "am",
        "hững",
        "hóm",
        "hóm",
        "hóm",
        "hóm",
        "ày",
        "hân",
        "hất,",
        "hóm",
        "gười",
        "ăm",
        "ăm",
        "hững",
        "hóm",
        "ăm",
        "hất",
        "ăm",
        "hóm",
        "hất,",
        "hóm",
        "hất",
        "hóm",
        "ào,.",
        "hóm",
        "hóm",
        "hóm",
        "ăng",
        "guy"
    ],
    "t": [
        "hù",
        "hù",
        "ổ",
        "hực",
        "hù",
        "hành",
        "ộc,",
        "ộc,",
        "ôn",
        "ính,",
        "hiên",
        "ình",
        "ượng,",
        "hể",
        "heo",
        "hù",
        "húc",
        "hù",
        "huộc",
        "ộc,",
        "ôn",
        "ật,",
        "huộc",
        "ình",
        "ộc/quốc",
        "hành",
        "âm",
        "hù",
        "in",
        "ấn",
        "oàn",
        "hường",
        "hể",
        "hay",
        "ại",
        "ổ",
        "hù",
        "ắt:",
        "âm",
        "ắt:",
        "hù",
        "heo",
        "ừ",
        "hù",
        "hấy",
        "ăng",
        "ổng",
        "hù",
        "hể",
        "oàn",
        "ham",
        "ội",
        "háng",
        "hù",
        "ại",
        "hấp",
        "ừ",
        "hù",
        "iểu",
        "iểu",
        "hù",
        "hù",
        "heo",
        "hù",
        "hực",
        "hực",
        "hực",
        "ạo",
        "ham"
    ],
    "gh": [
        "ét,",
        "ét,",
        "ét,",
        "ét\"",
        "ét",
        "ét.",
        "ét",
        "ét",
        "ét",
        "ét",
        "ét",
        "ét",
        "ét,"
    ],
    "h": [
        "ay",
        "ận,",
        "oặc",
        "ộ",
        "ay",
        "iện",
        "ận",
        "oặc",
        "ướng",
        "oặc",
        "ội.",
        "oa",
        "ận",
        "ướng",
        "ay",
        "oa",
        "oặc",
        "ành",
        "ay",
        "ội,",
        "ọ.",
        "oa",
        "oa",
        "ai",
        "oa",
        "ạng",
        "oạt",
        "oạt",
        "ộ",
        "oặc",
        "oạt",
        "oặc",
        "àng",
        "ay",
        "oạt",
        "oa",
        "iện",
        "ơn",
        "awaii",
        "ai",
        "iện",
        "oặc",
        "ành",
        "iện,",
        "iện",
        "ành",
        "ành"
    ],
    "l": [
        "à",
        "òng",
        "ực",
        "ĩnh",
        "iên",
        "à",
        "uật",
        "à",
        "ợi",
        "eague,",
        "uật",
        "aw",
        "ượng",
        "ực",
        "à",
        "ực",
        "ượng",
        "uật",
        "iên"
    ],
    "m": [
        "ột",
        "ột",
        "ột",
        "ột",
        "ột",
        "iền",
        "ột",
        "ột",
        "iền",
        "ột",
        "ỹ,",
        "ột",
        "ức",
        "ỗi",
        "ột",
        "ối"
    ],
    "c": [
        "ó",
        "ăm",
        "ác",
        "ủa",
        "ó",
        "ục",
        "ủa",
        "ăm",
        "ác",
        "ác",
        "ủa",
        "ứu",
        "ó",
        "ác",
        "ông",
        "ủa",
        "ác",
        "ứu",
        "enter,",
        "ác",
        "ác",
        "ó",
        "á",
        "ác",
        "áo",
        "ông",
        "on",
        "alifornia",
        "ó",
        "ác",
        "ao",
        "ó",
        "ác",
        "ũng",
        "ông",
        "ủa",
        "ác",
        "ó",
        "ủa",
        "ó",
        "ác",
        "ông",
        "ơ"
    ],
    "ch": [
        "ức",
        "ủng",
        "ính",
        "ủng",
        "ức",
        "ống",
        "ỉ",
        "o",
        "ỉ"
    ],
    "ủ": [
        "ng",
        "ng"
    ],
    "ph": [
        "ong",
        "ỉ",
        "ỉ",
        "ần",
        "ạm",
        "ạm"
    ],
    "tr": [
        "ào",
        "ong",
        "a",
        "ung",
        "ong",
        "ung",
        "ì",
        "ong",
        "ăm",
        "ong",
        "a"
    ],
    "á": [
        "p",
        "c",
        "m"
    ],
    "d": [
        "ụng",
        "ục",
        "anh",
        "ục,",
        "ân",
        "ụng",
        "uy",
        "anh",
        "uy",
        "uy",
        "õi",
        "anh",
        "ọa"
    ],
    "b": [
        "ạo",
        "ất",
        "ang",
        "ởi",
        "ao",
        "áng",
        "ộ",
        "ao",
        "áng''",
        "ao",
        "ộ",
        "ạo",
        "ản",
        "áo",
        "ố",
        "ang.",
        "ang",
        "ởi",
        "ố",
        "ố;",
        "ang.\""
    ],
    "đ": [
        "ối",
        "ối",
        "ịnh",
        "iều",
        "ích",
        "ẩy",
        "ịch",
        "ối",
        "ịnh",
        "ộng",
        "ặc",
        "iểm",
        "ổi",
        "ược",
        "oàn",
        "oạn",
        "ến",
        "ộng",
        "ộng,",
        "ộng",
        "ầu",
        "ộng",
        "ang",
        "ược",
        "iều",
        "ược",
        "e",
        "ộng",
        "ược",
        "ể",
        "ộng",
        "ộng"
    ],
    "v": [
        "ới",
        "iên",
        "ực",
        "à",
        "ới",
        "iên",
        "iết",
        "à",
        "iết",
        "à",
        "ới",
        "ào",
        "à",
        "à",
        "ới",
        "à",
        "à",
        "ụ",
        "à",
        "i"
    ],
    "s": [
        "ắc",
        "ự",
        "át",
        "outhern",
        "plc).",
        "plc",
        "ách",
        "plc,",
        "át",
        "ố",
        "ố",
        "plc",
        "ố",
        "ố",
        "ách"
    ],
    "g": [
        "iáo,",
        "iới",
        "iáo,",
        "ia",
        "ồm",
        "iám",
        "ồm",
        "iai",
        "ồm",
        "ia",
        "iảm",
        "iữa"
    ],
    "k": [
        "ỳ",
        "ỳ",
        "ỳ",
        "ỳ",
        "ỳ,",
        "ỳ",
        "ỳ"
    ],
    "kh": [
        "ác",
        "uyết",
        "ác",
        "ông",
        "ông",
        "ác.",
        "ông",
        "ông",
        "i",
        "i",
        "ả",
        "i",
        "ảo"
    ],
    "x": [
        "ã",
        "u",
        "ã",
        "ếp"
    ],
    "(": [
        "fbi),",
        "splc)",
        "anti-defamation",
        "the"
    ],
    "\"": [
        "mục",
        "nhóm",
        "nghiệp"
    ],
    "ý": [
        ""
    ],
    "=": [
        "=",
        "=",
        "=",
        "="
    ],
    "'": [
        "'liên"
    ],
    "a": [
        "dl)",
        "dl",
        "laska"
    ],
    "p": [
        "overty"
    ],
    "2": [
        "008,",
        "015,",
        "014.",
        "005."
    ],
    "qu": [
        "an"
    ],
    "ở": [
        "",
        "",
        ""
    ],
    "1": [
        "7%"
    ],
    "f": [
        "lorida",
        "bi.",
        "bi"
    ],
    "r": [
        "õ",
        "àng",
        "a"
    ]
}