{
    "n": [
        "hóm",
        "guyên",
        "hóm",
        "guyên",
        "iobi",
        "hóm",
        "ày",
        "hóm"
    ],
    "t": [
        "ố",
        "ố",
        "antali",
        "uần",
        "ên",
        "ham"
    ],
    "l": [
        "à",
        "à"
    ],
    "g": [
        "ồm",
        "ọi"
    ],
    "v": [
        "anađi",
        "à",
        "anađi."
    ],
    "(": [
        "v),",
        "nb),",
        "ta)",
        "db)"
    ],
    "d": [
        "ubni"
    ],
    "tr": [
        "ong"
    ],
    "b": [
        "ảng"
    ],
    "h": [
        "oàn,"
    ],
    "c": [
        "òn",
        "ó"
    ],
    "kh": [
        "ác",
        "ảo"
    ],
    "=": [
        "=",
        "="
    ]
}