{
    "v": [
        "ườn",
        "iên\")",
        "ườn",
        "à",
        "ườn",
        "iên",
        "ườn",
        "iên"
    ],
    "qu": [
        "ốc",
        "ốc",
        "ốc",
        "yền",
        "ốc",
        "ần",
        "ốc"
    ],
    "g": [
        "ia",
        "ia",
        "ấu",
        "iữ).",
        "ia",
        "iới.",
        "iới.",
        "ia"
    ],
    "s": [
        "hiretoko",
        "hiretoko",
        "àng",
        "hiretoko",
        "hiretoko",
        "ố",
        "ản",
        "ản",
        "ông"
    ],
    "(": [
        "tiếng",
        "nhật",
        "tiếng"
    ],
    "n": [
        "hật:",
        "hật",
        "ghĩa",
        "ày",
        "hất",
        "hật",
        "hìn",
        "hưng",
        "ga",
        "ăm",
        "ày",
        "hận",
        "ghị",
        "ên",
        "ga",
        "ày",
        "ước",
        "óng",
        "ghĩa",
        "úi",
        "ày",
        "gọn",
        "úi",
        "hất",
        "hật",
        "hật",
        "goài"
    ],
    "知": [
        "床国立公園,"
    ],
    "k": [
        "okuritsu",
        "ōen;",
        "unashiri",
        "uril",
        "amuiwakkayu",
        "ết"
    ],
    "h": [
        "án-việt:",
        "okkaido,",
        "òa",
        "ttp://www.biodic.go.jp/english/jpark/np/siretoko_e.html"
    ],
    "\"": [
        "tri",
        "nơi",
        "công",
        "dòng"
    ],
    "l": [
        "ập",
        "à",
        "ượng",
        "oài",
        "ớn",
        "à",
        "à",
        "ửa",
        "à",
        "ịch",
        "iên"
    ],
    "c": [
        "ông",
        "ủa",
        "ó",
        "ùng",
        "ó",
        "ó",
        "ông",
        "ộng",
        "ủa",
        "ó",
        "ủa",
        "ông",
        "ao",
        "ao"
    ],
    "b": [
        "ao",
        "ọc",
        "án",
        "ắc",
        "ản.",
        "ản",
        "ản",
        "ình\"",
        "iên",
        "ản.",
        "ản"
    ],
    "ph": [
        "ần"
    ],
    "đ": [
        "ảo",
        "ông",
        "ảo",
        "ất\".",
        "ây",
        "ảo",
        "òi",
        "ang",
        "ược",
        "ảo",
        "ế\")."
    ],
    "t": [
        "ại",
        "iếng",
        "ận",
        "ừ",
        "hể",
        "hế",
        "hêm",
        "hành",
        "hác",
        "hượng",
        "hêm",
        "ham"
    ],
    "m": [
        "ũi",
        "ột",
        ",",
        "ột"
    ],
    "tr": [
        "ong",
        "ái",
        "ong",
        "ong",
        "ong"
    ],
    "a": [
        "inu",
        "inu"
    ],
    "r": [
        "a",
        "ausu"
    ],
    "ch": [
        "ủ",
        "iếm"
    ],
    "2": [
        "005,"
    ],
    "u": [
        "nesco",
        "nesco"
    ],
    "d": [
        "i",
        "i",
        "u"
    ],
    "kh": [
        "uyến",
        "ảo"
    ],
    "x": [
        "uyên",
        "em"
    ],
    "=": [
        "=",
        "=",
        "=",
        "=",
        "=",
        "="
    ]
}